marvinxu/__init__.py
marvinxu/common.py
marvinxu/pandas.py
marvinxu-0.2.3.dist-info/WHEEL
marvinxu-0.2.3.dist-info/METADATA
marvinxu-0.2.3.dist-info/RECORD
