Metadata-Version: 2.1
Name: marvinxu
Version: 0.2.3
Summary: Marvin's toolkit
License: MIT
Author-email: MarvinXu <272077995@qq.com>
Requires-Python: >=3.10
